zenonfox/__init__.py
zenonfox/banner.py
zenonfox/base.py
zenonfox-1.7.0.dist-info/LICENSE
zenonfox-1.7.0.dist-info/METADATA
zenonfox-1.7.0.dist-info/WHEEL
zenonfox-1.7.0.dist-info/top_level.txt
zenonfox-1.7.0.dist-info/RECORD
