Metadata-Version: 2.1
Name: zenonfox
Version: 1.7.0
Summary: zenon Air Drop BOT
Home-page: https://github.com/foxZenonn
Author: foxzenon
Author-email: zoogaming00@gmail.com
License: MIT license
Classifier: Programming Language :: Python :: 3
Classifier: License :: OSI Approved :: MIT License
Classifier: Operating System :: OS Independent
License-File: LICENSE
